prolog_kernel/__init__.py
prolog_kernel/__main__.py
prolog_kernel/install.py
prolog_kernel/kernel.py
prolog_kernel/prolog_kernel_base_implementation.py
prolog_kernel/prolog_kernel_config.py
prolog_kernel/sicstus_kernel_implementation.py
prolog_kernel/swi_kernel_implementation.py
prolog_kernel/kernelspec/kernel.js
prolog_kernel/kernelspec/kernel.json
prolog_kernel/prolog_server/jupyter.pl
prolog_kernel/prolog_server/jupyter_jsonrpc.pl
prolog_kernel/prolog_server/jupyter_logging.pl
prolog_kernel/prolog_server/jupyter_query_handling.pl
prolog_kernel/prolog_server/jupyter_request_handling.pl
prolog_kernel/prolog_server/jupyter_server.pl
prolog_kernel/prolog_server/jupyter_server_tests.pl
prolog_kernel/prolog_server/jupyter_term_handling.pl
prolog_kernel/prolog_server/jupyter_variable_bindings.pl
prolog_kernel/prolog_server/test.pl
prolog_kernel-0.0.9.dist-info/LICENSE
prolog_kernel-0.0.9.dist-info/METADATA
prolog_kernel-0.0.9.dist-info/WHEEL
prolog_kernel-0.0.9.dist-info/top_level.txt
prolog_kernel-0.0.9.dist-info/RECORD
