Metadata-Version: 2.1
Name: prolog-kernel
Version: 0.0.9
Summary: Extensible Jupyter kernel for (SWI- and SICStus) Prolog
Author: Anne Brecklinghaus
License: Copyright (c) 2018 The Python Packaging Authority        
Project-URL: Homepage, https://github.com/anbre/prolog-jupyter-kernel
Classifier: Programming Language :: Python :: 3
Classifier: License :: OSI Approved :: MIT License
Classifier: Operating System :: OS Independent
Classifier: Intended Audience :: Developers
Requires-Python: >=3.7
License-File: LICENSE
Requires-Dist: jupyter-client
Requires-Dist: IPython
Requires-Dist: ipykernel
Requires-Dist: graphviz
Requires-Dist: beautifulsoup4
